dyn/events/__init__.py
dyn/events/events_calculator.py
dyn/events/icem_calculator.py
dyn/events/main_compute_events.py
dyn/events/masks.py
dyn/temporal_clustering/__init__.py
dyn/temporal_clustering/build_community_graph.py
dyn/temporal_clustering/community_detection.py
dyn/temporal_clustering/generate_experiments.py
dyn_analysis-0.0.3.dist-info/licenses/LICENSE
dyn_analysis-0.0.3.dist-info/METADATA
dyn_analysis-0.0.3.dist-info/WHEEL
dyn_analysis-0.0.3.dist-info/top_level.txt
dyn_analysis-0.0.3.dist-info/RECORD
