Metadata-Version: 2.4
Name: dyn-analysis
Version: 0.0.3
Summary: Analysis features of the 'dyn' namespace package
Author-email: Cécile Bothorel <cecile.bothorel@imt-atlantique.fr>, Laurent Brisson <laurent.brisson@imt-atlantique.fr>, Nicolas Duminy <nicolas.duminy@imt-atlantique.fr>
License: Copyright IMT Atlantique, 2021
Project-URL: Documentation, https://dyn-analysis.readthedocs.io/en/latest/
Project-URL: Homepage, https://gitlab.com/decide.imt-atlantique/dyn/analysis
Project-URL: Issues, https://gitlab.com/decide.imt-atlantique/dyn/analysis/issues
Classifier: Development Status :: 4 - Beta
Classifier: Intended Audience :: Developers
Classifier: Intended Audience :: Science/Research
Classifier: License :: OSI Approved :: European Union Public Licence 1.2 (EUPL 1.2)
Classifier: Operating System :: OS Independent
Classifier: Programming Language :: Python :: 3
Classifier: Programming Language :: Python :: 3 :: Only
Requires-Python: >=3.8
License-File: LICENSE
Requires-Dist: dyn-core>=0.1
Requires-Dist: pandas
Requires-Dist: igraph
Dynamic: license-file
